{
  "type": "silentgear:standard",
  "simple": true,
  "harvest_tier": "minecraft:diamond",
  "availability": {
    "tier": 5,
    "categories": [
      "metal"
    ],
    "visible": true,
    "gear_blacklist": [],
    "can_salvage": true
  },
  "crafting_items": {
    "main": {
      "item": "terrawhips_and_more:frostcore"
    }
  },
  "name": {
    "translate": "寒霜核心"
  },
  "stats": {
    "main": {
      "durability": 2000.0,
      "armor_durability": 300.0,
      "enchantment_value": 16.0,
      "rarity": 65.0,
      "charging_value": 1.0,
      "repair_value": 0.45,
      "harvest_speed": 10.0,
      "melee_damage": 24.5,
      "magic_damage": 2.5,
      "attack_speed": 0.0,
      "attack_speed/hoe": 1.0,
      "ranged_damage": 3.0,
      "ranged_speed": -0.1,
      "projectile_speed": 1.1,
      "projectile_accuracy": 0.9,
      "armor": 48,
      "armor_toughness": 2.0,
      "magic_armor": 6.0
    },
    "rod": {},
    "tip": {
      "durability": {
        "add": 512.0
      },
      "attack_speed": {
        "add": 0.1
      },
      "melee_damage": {
        "add": 5.0
      },
      "magic_damage": {
        "add": 2.0
      },
      "ranged_damage": {
        "add": 1.0
      }
    }
  },
  "traits": {
    "main": [
      {
        "name": "tales_of_element:frost_damage",
        "level": 5,
        "conditions": [
          {
            "type": "silentgear:and",
            "values": [
              {
                "type": "silentgear:material_ratio",
                "ratio": 0.6
              },
              {
                "type": "silentgear:gear_type",
                "gear_type": "melee_weapon"
              }
            ]
          }
        ]
      },
      {
        "name": "tales_of_element:frost_armor",
        "level": 3,
        "conditions": [
          {
            "type": "silentgear:and",
            "values": [
              {
                "type": "silentgear:material_ratio",
                "ratio": 0.6
              },
              {
                "type": "silentgear:gear_type",
                "gear_type": "armor"
              }
            ]
          }
        ]
      },
      {
        "name": "tales_of_element:fire_weak",
        "level": 3,
        "conditions": [
          {
            "type": "silentgear:and",
            "values": [
              {
                "type": "silentgear:material_ratio",
                "ratio": 0.6
              },
              {
                "type": "silentgear:gear_type",
                "gear_type": "armor"
              }
            ]
          }
        ]
      },
      {
        "name": "tales_of_element:ray_of_frost",
        "level": 2,
        "conditions": [
          {
            "type": "silentgear:and",
            "values": [
              {
                "type": "silentgear:material_ratio",
                "ratio": 0.6
              },
              {
                "type": "silentgear:gear_type",
                "gear_type": "chestplate"
              }
            ]
          }
        ]
      },
      {
        "name": "tales_of_element:ice_fragment",
        "level": 1,
        "conditions": [
          {
            "type": "silentgear:and",
            "values": [
              {
                "type": "silentgear:material_ratio",
                "ratio": 0.6
              }
            ]
          }
        ]
      }
    ],
    "rod": [
      {
        "name": "tales_of_element:frost_damage",
        "level": 1,
        "conditions": [
          {
            "type": "silentgear:material_ratio",
            "ratio": 0.5
          }
        ]
      }
    ],
    "tip": [
      {
        "name": "tales_of_element:frost_damage",
        "level": 2,
        "conditions": [
          {
            "type": "silentgear:and",
            "values": [
              {
                "type": "silentgear:material_ratio",
                "ratio": 0.6
              },
              {
                "type": "silentgear:gear_type",
                "gear_type": "melee_weapon"
              }
            ]
          }
        ]
      }
    ]
  },
  "model": {
    "main/all": [
      {
        "texture": "silentgear:main_generic_hc",
        "color": "#2768ED"
      },
      {
        "texture": "silentgear:_highlight"
      }
    ],
    "main/fragment": [
      {
        "texture": "silentgear:metal",
        "color": "#2768ED"
      }
    ],
    "rod/all": [
      {
        "texture": "silentgear:rod_generic_lc",
        "color": "#2768ED"
      }
    ],
    "rod/part": [
      {
        "texture": "silentgear:rod",
        "color": "#2768ED"
      }
    ],
    "tip/all": [
      {
        "texture": "silentgear:tip_frost",
        "color": "#2768ED"
      }
    ],
    "tip/part": [
      {
        "texture": "silentgear:tip_base"
      },
      {
        "texture": "silentgear:tip",
        "color": "#2768ED"
      },
      {
        "texture": "silentgear:tip_shine"
      }
    ]
  }
}